AUTHORS.rst
CHANGELOG.rst
LICENSE
MANIFEST.in
README.rst
setup.py
django_likes.egg-info/PKG-INFO
django_likes.egg-info/SOURCES.txt
django_likes.egg-info/dependency_links.txt
django_likes.egg-info/not-zip-safe
django_likes.egg-info/requires.txt
django_likes.egg-info/top_level.txt
likes/__init__.py
likes/exceptions.py
likes/middleware.py
likes/models.py
likes/signals.py
likes/urls.py
likes/utils.py
likes/views.py
likes/static/likes/includes/likes.js
likes/templates/likes/inclusion_tags/likes.html
likes/templates/likes/inclusion_tags/likes_extender.html
likes/templatetags/__init__.py
likes/templatetags/__init__.pyc
likes/templatetags/likes_inclusion_tags.py
likes/tests/__init__.py
likes/tests/manage.py
likes/tests/models.py
likes/tests/test_views.py
likes/tests/requirements/110.txt
likes/tests/requirements/111.txt
likes/tests/requirements/18.txt
likes/tests/requirements/19.txt
likes/tests/requirements/20.txt
likes/tests/settings/110.py
likes/tests/settings/111.py
likes/tests/settings/18.py
likes/tests/settings/19.py
likes/tests/settings/19.pyc
likes/tests/settings/20.py
likes/tests/settings/__init__.py
likes/tests/settings/__init__.pyc