Metadata-Version: 1.1
Name: django-likes
Version: 2.0.0
Summary: Django app providing view interface to django-secretballot.
Home-page: http://github.com/praekelt/django-likes
Author: Praekelt Foundation
Author-email: dev@praekelt.com
License: BSD
Platform: UNKNOWN
Classifier: Programming Language :: Python
Classifier: License :: OSI Approved :: BSD License
Classifier: Development Status :: 4 - Beta
Classifier: Operating System :: OS Independent
Classifier: Framework :: Django
Classifier: Intended Audience :: Developers
Classifier: Topic :: Internet :: WWW/HTTP :: Dynamic Content
